asgi_testclient/__init__.py
asgi_testclient/client.py
asgi_testclient/sync.py
asgi_testclient/types.py
asgi_testclient-0.3.1.dist-info/LICENSE
asgi_testclient-0.3.1.dist-info/WHEEL
asgi_testclient-0.3.1.dist-info/METADATA
asgi_testclient-0.3.1.dist-info/RECORD
